cryspy/__init__.py
cryspy/BO/__init__.py
cryspy/BO/bo_init.py
cryspy/BO/bo_next_select.py
cryspy/BO/bo_restart.py
cryspy/BO/select_descriptor.py
cryspy/EA/__init__.py
cryspy/EA/calc_ef.py
cryspy/EA/calc_hull.py
cryspy/EA/ea_append.py
cryspy/EA/ea_child.py
cryspy/EA/ea_init.py
cryspy/EA/ea_next_gen.py
cryspy/EA/survival.py
cryspy/EA/gen_struc_EA/__init__.py
cryspy/EA/gen_struc_EA/addition.py
cryspy/EA/gen_struc_EA/crossover.py
cryspy/EA/gen_struc_EA/elimination.py
cryspy/EA/gen_struc_EA/permutation.py
cryspy/EA/gen_struc_EA/rotation.py
cryspy/EA/gen_struc_EA/select_parents.py
cryspy/EA/gen_struc_EA/strain.py
cryspy/EA/gen_struc_EA/substitution.py
cryspy/IO/__init__.py
cryspy/IO/change_input.py
cryspy/IO/diff_input.py
cryspy/IO/io_stat.py
cryspy/IO/out_results.py
cryspy/IO/pkl_data.py
cryspy/IO/read_input.py
cryspy/IO/write_input.py
cryspy/LAQA/__init__.py
cryspy/LAQA/calc_score.py
cryspy/LAQA/laqa_init.py
cryspy/LAQA/laqa_next_selection.py
cryspy/LAQA/laqa_restart.py
cryspy/RS/__init__.py
cryspy/RS/rs_gen.py
cryspy/RS/rs_init.py
cryspy/RS/rs_restart.py
cryspy/RS/gen_struc_RS/__init__.py
cryspy/RS/gen_struc_RS/gen_pyxtal.py
cryspy/RS/gen_struc_RS/random_generation.py
cryspy/calc_dscrpt/__init__.py
cryspy/calc_dscrpt/FP/__init__.py
cryspy/calc_dscrpt/FP/calc_FP.py
cryspy/interactive/__init__.py
cryspy/interactive/action.py
cryspy/interactive/energy_plot.py
cryspy/interactive/manage_structure.py
cryspy/interactive/opt_ase.py
cryspy/interactive/restart_interact.py
cryspy/interactive/show_dist.py
cryspy/interface/__init__.py
cryspy/interface/select_code.py
cryspy/interface/ASE/calc_files_ase.py
cryspy/interface/ASE/collect_ase.py
cryspy/interface/ASE/ctrl_job_ase.py
cryspy/interface/LAMMPS/__init__.py
cryspy/interface/LAMMPS/calc_files_lammps.py
cryspy/interface/LAMMPS/collect_lammps.py
cryspy/interface/LAMMPS/ctrl_job_lammps.py
cryspy/interface/LAMMPS/structure.py
cryspy/interface/OMX/calc_files_OMX.py
cryspy/interface/OMX/collect_OMX.py
csp_cryspy-1.4.1.dist-info/licenses/LICENSE
csp_cryspy-1.4.1.dist-info/METADATA
csp_cryspy-1.4.1.dist-info/WHEEL
csp_cryspy-1.4.1.dist-info/entry_points.txt
csp_cryspy-1.4.1.dist-info/top_level.txt
csp_cryspy-1.4.1.dist-info/RECORD
