Metadata-Version: 2.4
Name: csp-cryspy
Version: 1.4.1
Summary: CrySPY is a crystal structure prediction tool written in Python.
Author-email: Tomoki Yamashita <yamashita06@vos.nagaokaut.ac.jp>
Maintainer-email: Tomoki Yamashita <yamashita06@vos.nagaokaut.ac.jp>
License: MIT License
Project-URL: documentation, https://tomoki-yamashita.github.io/CrySPY_doc
Project-URL: repository, https://github.com/Tomoki-YAMASHITA/CrySPY.git
Project-URL: changelog, https://github.com/Tomoki-YAMASHITA/CrySPY/blob/master/CHANGELOG.md
Keywords: CSP
Classifier: Programming Language :: Python :: 3
Requires-Python: >=3.9
License-File: LICENSE
Requires-Dist: pyxtal>=0.5.3
Dynamic: license-file
